Workbook

Sheet README
A1: Hospital Parking Revenue Reconciliation & Variance Dashboard
A2: Portfolio project by Shailanshi Gupta | Built in Excel | ALL DATA IS SYNTHETIC (mock data for demonstration only)
A4: Purpose | B4: Demonstrates the monthly workflow of a hospital parking revenue control analyst: reconciling public parking account invoices to collections, analyzing revenue vs. budget variances by location, and reconciling employee parking access against payroll deductions.
A5: Data | B5: All accounts, locations, and amounts are invented for illustration. No real hospital, patient, employee, or vendor data is used.
A6: How it works | B6: Blue cells are inputs (mock data). Black cells are formulas. Change any blue input and every reconciliation status, variance, KPI, and chart updates automatically.
A7: Assumptions | B7: Tolerances and rates live on the Assumptions sheet and are referenced by every formula (no hardcoded thresholds).
A8: Sheets | B8: Assumptions | Invoice_Recon (account-level invoice vs. collection reconciliation) | Budget_vs_Actual (location revenue variance) | Employee_Access (permits vs. payroll deductions) | Dashboard (KPIs, exception summary, charts).
A9: Key questions answered | B9: Which accounts were under- or over-paid, and by how much? Which months and locations missed budget? How many active employee permits are not being billed through payroll, and what is the estimated revenue leakage?

Sheet Dashboard
A1: Parking Revenue Control Dashboard (Jan-Sep 2026)
A2: Synthetic data | All figures are live formulas linked to the reconciliation sheets
A4: KEY METRICS | D4: MONTHLY SUMMARY
A5: Total Billed | B5: =SUM(Invoice_Recon!D5:D76) -> 679220 | D5: Month | E5: Billed ($) | F5: Collected ($) | G5: Variance ($) | H5: Exceptions (#) | I5: Budget ($) | J5: Actual ($) | K5: Budget Var %
A6: Total Collected | B6: =SUM(Invoice_Recon!E5:E76) -> 659246 | D6: Jan-2026 | E6: =SUMIFS(Invoice_Recon!$D$5:$D$76,Invoice_Recon!$C$5:$C$76,$D6) -> 75410 | F6: =SUMIFS(Invoice_Recon!$E$5:$E$76,Invoice_Recon!$C$5:$C$76,$D6) -> 75314 | G6: =F6-E6 -> -96 | H6: =COUNTIFS(Invoice_Recon!$C$5:$C$76,$D6,Invoice_Recon!$H$5:$H$76,"<>Matched") -> 0 | I6: =SUMIFS(Budget_vs_Actual!$C$5:$C$40,Budget_vs_Actual!$B$5:$B$40,$D6) -> 320100 | J6: =SUMIFS(Budget_vs_Actual!$D$5:$D$40,Budget_vs_Actual!$B$5:$B$40,$D6) -> 321290 | K6: =IFERROR(J6/I6-1,0) -> 0.0037175883
A7: Collection Rate | B7: =IFERROR(B6/B5,0) -> 0.97059274 | D7: Feb-2026 | E7: =SUMIFS(Invoice_Recon!$D$5:$D$76,Invoice_Recon!$C$5:$C$76,$D7) -> 75720 | F7: =SUMIFS(Invoice_Recon!$E$5:$E$76,Invoice_Recon!$C$5:$C$76,$D7) -> 75063 | G7: =F7-E7 -> -657 | H7: =COUNTIFS(Invoice_Recon!$C$5:$C$76,$D7,Invoice_Recon!$H$5:$H$76,"<>Matched") -> 1 | I7: =SUMIFS(Budget_vs_Actual!$C$5:$C$40,Budget_vs_Actual!$B$5:$B$40,$D7) -> 313400 | J7: =SUMIFS(Budget_vs_Actual!$D$5:$D$40,Budget_vs_Actual!$B$5:$B$40,$D7) -> 309100 | K7: =IFERROR(J7/I7-1,0) -> -0.013720485
A8: Net Invoice Variance | B8: =B6-B5 -> -19974 | D8: Mar-2026 | E8: =SUMIFS(Invoice_Recon!$D$5:$D$76,Invoice_Recon!$C$5:$C$76,$D8) -> 76950 | F8: =SUMIFS(Invoice_Recon!$E$5:$E$76,Invoice_Recon!$C$5:$C$76,$D8) -> 75144 | G8: =F8-E8 -> -1806 | H8: =COUNTIFS(Invoice_Recon!$C$5:$C$76,$D8,Invoice_Recon!$H$5:$H$76,"<>Matched") -> 2 | I8: =SUMIFS(Budget_vs_Actual!$C$5:$C$40,Budget_vs_Actual!$B$5:$B$40,$D8) -> 337000 | J8: =SUMIFS(Budget_vs_Actual!$D$5:$D$40,Budget_vs_Actual!$B$5:$B$40,$D8) -> 339740 | K8: =IFERROR(J8/I8-1,0) -> 0.0081305638
A9: Invoice Exceptions (#) | B9: =COUNTIF(Invoice_Recon!H5:H76,"<>Matched") -> 9 | D9: Apr-2026 | E9: =SUMIFS(Invoice_Recon!$D$5:$D$76,Invoice_Recon!$C$5:$C$76,$D9) -> 74480 | F9: =SUMIFS(Invoice_Recon!$E$5:$E$76,Invoice_Recon!$C$5:$C$76,$D9) -> 74327 | G9: =F9-E9 -> -153 | H9: =COUNTIFS(Invoice_Recon!$C$5:$C$76,$D9,Invoice_Recon!$H$5:$H$76,"<>Matched") -> 1 | I9: =SUMIFS(Budget_vs_Actual!$C$5:$C$40,Budget_vs_Actual!$B$5:$B$40,$D9) -> 340400 | J9: =SUMIFS(Budget_vs_Actual!$D$5:$D$40,Budget_vs_Actual!$B$5:$B$40,$D9) -> 343780 | K9: =IFERROR(J9/I9-1,0) -> 0.0099294947
A10: Gross Exception Amount | B10: =SUMPRODUCT((Invoice_Recon!H5:H76<>"Matched")*ABS(Invoice_Recon!F5:F76)) -> 21330 | D10: May-2026 | E10: =SUMIFS(Invoice_Recon!$D$5:$D$76,Invoice_Recon!$C$5:$C$76,$D10) -> 73180 | F10: =SUMIFS(Invoice_Recon!$E$5:$E$76,Invoice_Recon!$C$5:$C$76,$D10) -> 64022 | G10: =F10-E10 -> -9158 | H10: =COUNTIFS(Invoice_Recon!$C$5:$C$76,$D10,Invoice_Recon!$H$5:$H$76,"<>Matched") -> 1 | I10: =SUMIFS(Budget_vs_Actual!$C$5:$C$40,Budget_vs_Actual!$B$5:$B$40,$D10) -> 347100 | J10: =SUMIFS(Budget_vs_Actual!$D$5:$D$40,Budget_vs_Actual!$B$5:$B$40,$D10) -> 334340 | K10: =IFERROR(J10/I10-1,0) -> -0.03676174
A11: Revenue vs. Budget (YTD) | B11: =SUM(Budget_vs_Actual!D5:D40)-SUM(Budget_vs_Actual!C5:C40) -> -20910 | D11: Jun-2026 | E11: =SUMIFS(Invoice_Recon!$D$5:$D$76,Invoice_Recon!$C$5:$C$76,$D11) -> 74570 | F11: =SUMIFS(Invoice_Recon!$E$5:$E$76,Invoice_Recon!$C$5:$C$76,$D11) -> 74844 | G11: =F11-E11 -> 274 | H11: =COUNTIFS(Invoice_Recon!$C$5:$C$76,$D11,Invoice_Recon!$H$5:$H$76,"<>Matched") -> 1 | I11: =SUMIFS(Budget_vs_Actual!$C$5:$C$40,Budget_vs_Actual!$B$5:$B$40,$D11) -> 343700 | J11: =SUMIFS(Budget_vs_Actual!$D$5:$D$40,Budget_vs_Actual!$B$5:$B$40,$D11) -> 345750 | K11: =IFERROR(J11/I11-1,0) -> 0.0059645039
A12: Location-Months Flagged | B12: =COUNTIF(Budget_vs_Actual!G5:G40,"<>Within Range") -> 4 | D12: Jul-2026 | E12: =SUMIFS(Invoice_Recon!$D$5:$D$76,Invoice_Recon!$C$5:$C$76,$D12) -> 76210 | F12: =SUMIFS(Invoice_Recon!$E$5:$E$76,Invoice_Recon!$C$5:$C$76,$D12) -> 76585 | G12: =F12-E12 -> 375 | H12: =COUNTIFS(Invoice_Recon!$C$5:$C$76,$D12,Invoice_Recon!$H$5:$H$76,"<>Matched") -> 1 | I12: =SUMIFS(Budget_vs_Actual!$C$5:$C$40,Budget_vs_Actual!$B$5:$B$40,$D12) -> 330300 | J12: =SUMIFS(Budget_vs_Actual!$D$5:$D$40,Budget_vs_Actual!$B$5:$B$40,$D12) -> 321170 | K12: =IFERROR(J12/I12-1,0) -> -0.027641538
A13: Est. Unbilled Employee Permits ($) | B13: =Employee_Access!E14 -> 1235 | D13: Aug-2026 | E13: =SUMIFS(Invoice_Recon!$D$5:$D$76,Invoice_Recon!$C$5:$C$76,$D13) -> 75180 | F13: =SUMIFS(Invoice_Recon!$E$5:$E$76,Invoice_Recon!$C$5:$C$76,$D13) -> 67849 | G13: =F13-E13 -> -7331 | H13: =COUNTIFS(Invoice_Recon!$C$5:$C$76,$D13,Invoice_Recon!$H$5:$H$76,"<>Matched") -> 1 | I13: =SUMIFS(Budget_vs_Actual!$C$5:$C$40,Budget_vs_Actual!$B$5:$B$40,$D13) -> 326900 | J13: =SUMIFS(Budget_vs_Actual!$D$5:$D$40,Budget_vs_Actual!$B$5:$B$40,$D13) -> 326210 | K13: =IFERROR(J13/I13-1,0) -> -0.0021107372
D14: Sep-2026 | E14: =SUMIFS(Invoice_Recon!$D$5:$D$76,Invoice_Recon!$C$5:$C$76,$D14) -> 77520 | F14: =SUMIFS(Invoice_Recon!$E$5:$E$76,Invoice_Recon!$C$5:$C$76,$D14) -> 76098 | G14: =F14-E14 -> -1422 | H14: =COUNTIFS(Invoice_Recon!$C$5:$C$76,$D14,Invoice_Recon!$H$5:$H$76,"<>Matched") -> 1 | I14: =SUMIFS(Budget_vs_Actual!$C$5:$C$40,Budget_vs_Actual!$B$5:$B$40,$D14) -> 350400 | J14: =SUMIFS(Budget_vs_Actual!$D$5:$D$40,Budget_vs_Actual!$B$5:$B$40,$D14) -> 347010 | K14: =IFERROR(J14/I14-1,0) -> -0.0096746575
A17: EXCEPTIONS BY ACCOUNT
A18: Account | B18: Exceptions (#) | C18: Net Variance ($)
A19: Corporate Partner A | B19: =COUNTIFS(Invoice_Recon!$A$5:$A$76,$A19,Invoice_Recon!$H$5:$H$76,"<>Matched") -> 1 | C19: =SUMIFS(Invoice_Recon!$F$5:$F$76,Invoice_Recon!$A$5:$A$76,$A19) -> -1734
A20: Corporate Partner B | B20: =COUNTIFS(Invoice_Recon!$A$5:$A$76,$A20,Invoice_Recon!$H$5:$H$76,"<>Matched") -> 1 | C20: =SUMIFS(Invoice_Recon!$F$5:$F$76,Invoice_Recon!$A$5:$A$76,$A20) -> -1196
A21: Hotel Validation Program | B21: =COUNTIFS(Invoice_Recon!$A$5:$A$76,$A21,Invoice_Recon!$H$5:$H$76,"<>Matched") -> 1 | C21: =SUMIFS(Invoice_Recon!$F$5:$F$76,Invoice_Recon!$A$5:$A$76,$A21) -> -9216
A22: Event Parking - Conference Center | B22: =COUNTIFS(Invoice_Recon!$A$5:$A$76,$A22,Invoice_Recon!$H$5:$H$76,"<>Matched") -> 2 | C22: =SUMIFS(Invoice_Recon!$F$5:$F$76,Invoice_Recon!$A$5:$A$76,$A22) -> 256
A23: Rideshare Pickup Zone | B23: =COUNTIFS(Invoice_Recon!$A$5:$A$76,$A23,Invoice_Recon!$H$5:$H$76,"<>Matched") -> 1 | C23: =SUMIFS(Invoice_Recon!$F$5:$F$76,Invoice_Recon!$A$5:$A$76,$A23) -> -669
A24: Contractor Lot Permits | B24: =COUNTIFS(Invoice_Recon!$A$5:$A$76,$A24,Invoice_Recon!$H$5:$H$76,"<>Matched") -> 1 | C24: =SUMIFS(Invoice_Recon!$F$5:$F$76,Invoice_Recon!$A$5:$A$76,$A24) -> -7489
A25: Patient Family Pass Program | B25: =COUNTIFS(Invoice_Recon!$A$5:$A$76,$A25,Invoice_Recon!$H$5:$H$76,"<>Matched") -> 1 | C25: =SUMIFS(Invoice_Recon!$F$5:$F$76,Invoice_Recon!$A$5:$A$76,$A25) -> -220
A26: Medical Office Tenant C | B26: =COUNTIFS(Invoice_Recon!$A$5:$A$76,$A26,Invoice_Recon!$H$5:$H$76,"<>Matched") -> 1 | C26: =SUMIFS(Invoice_Recon!$F$5:$F$76,Invoice_Recon!$A$5:$A$76,$A26) -> 294

Sheet Assumptions
A1: Assumptions
A2: Edit yellow cells to change thresholds; all formulas reference these cells
A4: Assumption | B4: Value | C4: Note
A5: Invoice match tolerance (%) | B5: 0.01 | C5: Collections within +/-1% of billed are treated as Matched
A6: Budget variance flag threshold (%) | B6: 0.05 | C6: Location-months beyond +/-5% of budget are flagged
A7: Employee permit monthly rate ($) | B7: 95 | C7: Synthetic monthly parking deduction per active permit

Sheet Invoice_Recon
A1: Public Parking Accounts: Invoice vs. Collection Reconciliation
A2: Synthetic data | Billed and Collected are inputs (blue); Variance and Status are formulas
A4: Account | B4: Account Type | C4: Month | D4: Billed ($) | E4: Collected ($) | F4: Variance ($) | G4: Variance % | H4: Status
A5: Corporate Partner A | B5: Monthly contract | C5: Jan-2026 | D5: 19050 | E5: 18978 | F5: =E5-D5 -> -72 | G5: =IFERROR(F5/D5,0) -> -0.0037795276 | H5: =IF(E5=0,"Missing Payment",IF(ABS(G5)<=Assumptions!$B$5,"Matched",IF(F5<0,"Short Payment","Overpayment"))) -> Matched
A6: Corporate Partner A | B6: Monthly contract | C6: Feb-2026 | D6: 18100 | E6: 18060 | F6: =E6-D6 -> -40 | G6: =IFERROR(F6/D6,0) -> -0.0022099448 | H6: =IF(E6=0,"Missing Payment",IF(ABS(G6)<=Assumptions!$B$5,"Matched",IF(F6<0,"Short Payment","Overpayment"))) -> Matched
A7: Corporate Partner A | B7: Monthly contract | C7: Mar-2026 | D7: 19300 | E7: 17760 | F7: =E7-D7 -> -1540 | G7: =IFERROR(F7/D7,0) -> -0.079792746 | H7: =IF(E7=0,"Missing Payment",IF(ABS(G7)<=Assumptions!$B$5,"Matched",IF(F7<0,"Short Payment","Overpayment"))) -> Short Payment
A8: Corporate Partner A | B8: Monthly contract | C8: Apr-2026 | D8: 19140 | E8: 19200 | F8: =E8-D8 -> 60 | G8: =IFERROR(F8/D8,0) -> 0.0031347962 | H8: =IF(E8=0,"Missing Payment",IF(ABS(G8)<=Assumptions!$B$5,"Matched",IF(F8<0,"Short Payment","Overpayment"))) -> Matched
A9: Corporate Partner A | B9: Monthly contract | C9: May-2026 | D9: 17620 | E9: 17609 | F9: =E9-D9 -> -11 | G9: =IFERROR(F9/D9,0) -> -0.00062429058 | H9: =IF(E9=0,"Missing Payment",IF(ABS(G9)<=Assumptions!$B$5,"Matched",IF(F9<0,"Short Payment","Overpayment"))) -> Matched
A10: Corporate Partner A | B10: Monthly contract | C10: Jun-2026 | D10: 17470 | E10: 17431 | F10: =E10-D10 -> -39 | G10: =IFERROR(F10/D10,0) -> -0.0022323984 | H10: =IF(E10=0,"Missing Payment",IF(ABS(G10)<=Assumptions!$B$5,"Matched",IF(F10<0,"Short Payment","Overpayment"))) -> Matched
A11: Corporate Partner A | B11: Monthly contract | C11: Jul-2026 | D11: 18700 | E11: 18629 | F11: =E11-D11 -> -71 | G11: =IFERROR(F11/D11,0) -> -0.0037967914 | H11: =IF(E11=0,"Missing Payment",IF(ABS(G11)<=Assumptions!$B$5,"Matched",IF(F11<0,"Short Payment","Overpayment"))) -> Matched
A12: Corporate Partner A | B12: Monthly contract | C12: Aug-2026 | D12: 17900 | E12: 17921 | F12: =E12-D12 -> 21 | G12: =IFERROR(F12/D12,0) -> 0.0011731844 | H12: =IF(E12=0,"Missing Payment",IF(ABS(G12)<=Assumptions!$B$5,"Matched",IF(F12<0,"Short Payment","Overpayment"))) -> Matched
A13: Corporate Partner A | B13: Monthly contract | C13: Sep-2026 | D13: 18800 | E13: 18758 | F13: =E13-D13 -> -42 | G13: =IFERROR(F13/D13,0) -> -0.0022340426 | H13: =IF(E13=0,"Missing Payment",IF(ABS(G13)<=Assumptions!$B$5,"Matched",IF(F13<0,"Short Payment","Overpayment"))) -> Matched
A14: Corporate Partner B | B14: Monthly contract | C14: Jan-2026 | D14: 12470 | E14: 12501 | F14: =E14-D14 -> 31 | G14: =IFERROR(F14/D14,0) -> 0.0024859663 | H14: =IF(E14=0,"Missing Payment",IF(ABS(G14)<=Assumptions!$B$5,"Matched",IF(F14<0,"Short Payment","Overpayment"))) -> Matched
A15: Corporate Partner B | B15: Monthly contract | C15: Feb-2026 | D15: 11480 | E15: 11508 | F15: =E15-D15 -> 28 | G15: =IFERROR(F15/D15,0) -> 0.0024390244 | H15: =IF(E15=0,"Missing Payment",IF(ABS(G15)<=Assumptions!$B$5,"Matched",IF(F15<0,"Short Payment","Overpayment"))) -> Matched
A16: Corporate Partner B | B16: Monthly contract | C16: Mar-2026 | D16: 12660 | E16: 12644 | F16: =E16-D16 -> -16 | G16: =IFERROR(F16/D16,0) -> -0.0012638231 | H16: =IF(E16=0,"Missing Payment",IF(ABS(G16)<=Assumptions!$B$5,"Matched",IF(F16<0,"Short Payment","Overpayment"))) -> Matched
... A76: Medical Office Tenant C | B76: Monthly contract | C76: Sep-2026 | D76: 10830 | E76: 10794 | F76: =E76-D76 -> -36 | G76: =IFERROR(F76/D76,0) -> -0.0033240997 | H76: =IF(E76=0,"Missing Payment",IF(ABS(G76)<=Assumptions!$B$5,"Matched",IF(F76<0,"Short Payment","Overpayment"))) -> Matched

Sheet Budget_vs_Actual
A1: Parking Revenue: Budget vs. Actual by Location
A2: Synthetic data | Budget and Actual are inputs (blue); variance and flag are formulas
A4: Location | B4: Month | C4: Budget ($) | D4: Actual ($) | E4: Variance ($) | F4: Variance % | G4: Flag
A5: Garage North | B5: Jan-2026 | C5: 134900 | D5: 134790 | E5: =D5-C5 -> -110 | F5: =IFERROR(E5/C5,0) -> -0.00081541883 | G5: =IF(ABS(F5)>Assumptions!$B$6,IF(E5<0,"Under Budget - Review","Over Budget - Review"),"Within Range") -> Within Range
A6: Garage North | B6: Feb-2026 | C6: 132100 | D6: 128690 | E6: =D6-C6 -> -3410 | F6: =IFERROR(E6/C6,0) -> -0.025813777 | G6: =IF(ABS(F6)>Assumptions!$B$6,IF(E6<0,"Under Budget - Review","Over Budget - Review"),"Within Range") -> Within Range
A7: Garage North | B7: Mar-2026 | C7: 142000 | D7: 144220 | E7: =D7-C7 -> 2220 | F7: =IFERROR(E7/C7,0) -> 0.015633803 | G7: =IF(ABS(F7)>Assumptions!$B$6,IF(E7<0,"Under Budget - Review","Over Budget - Review"),"Within Range") -> Within Range
A8: Garage North | B8: Apr-2026 | C8: 143400 | D8: 145690 | E8: =D8-C8 -> 2290 | F8: =IFERROR(E8/C8,0) -> 0.015969317 | G8: =IF(ABS(F8)>Assumptions!$B$6,IF(E8<0,"Under Budget - Review","Over Budget - Review"),"Within Range") -> Within Range
A9: Garage North | B9: May-2026 | C9: 146300 | D9: 143040 | E9: =D9-C9 -> -3260 | F9: =IFERROR(E9/C9,0) -> -0.02228298 | G9: =IF(ABS(F9)>Assumptions!$B$6,IF(E9<0,"Under Budget - Review","Over Budget - Review"),"Within Range") -> Within Range
A10: Garage North | B10: Jun-2026 | C10: 144800 | D10: 144590 | E10: =D10-C10 -> -210 | F10: =IFERROR(E10/C10,0) -> -0.0014502762 | G10: =IF(ABS(F10)>Assumptions!$B$6,IF(E10<0,"Under Budget - Review","Over Budget - Review"),"Within Range") -> Within Range
A11: Garage North | B11: Jul-2026 | C11: 139200 | D11: 128060 | E11: =D11-C11 -> -11140 | F11: =IFERROR(E11/C11,0) -> -0.080028736 | G11: =IF(ABS(F11)>Assumptions!$B$6,IF(E11<0,"Under Budget - Review","Over Budget - Review"),"Within Range") -> Under Budget - Review
A12: Garage North | B12: Aug-2026 | C12: 137700 | D12: 137930 | E12: =D12-C12 -> 230 | F12: =IFERROR(E12/C12,0) -> 0.0016702977 | G12: =IF(ABS(F12)>Assumptions!$B$6,IF(E12<0,"Under Budget - Review","Over Budget - Review"),"Within Range") -> Within Range
A13: Garage North | B13: Sep-2026 | C13: 147700 | D13: 148640 | E13: =D13-C13 -> 940 | F13: =IFERROR(E13/C13,0) -> 0.0063642519 | G13: =IF(ABS(F13)>Assumptions!$B$6,IF(E13<0,"Under Budget - Review","Over Budget - Review"),"Within Range") -> Within Range
A14: Garage South | B14: Jan-2026 | C14: 112100 | D14: 115220 | E14: =D14-C14 -> 3120 | F14: =IFERROR(E14/C14,0) -> 0.027832293 | G14: =IF(ABS(F14)>Assumptions!$B$6,IF(E14<0,"Under Budget - Review","Over Budget - Review"),"Within Range") -> Within Range
A15: Garage South | B15: Feb-2026 | C15: 109700 | D15: 112520 | E15: =D15-C15 -> 2820 | F15: =IFERROR(E15/C15,0) -> 0.025706472 | G15: =IF(ABS(F15)>Assumptions!$B$6,IF(E15<0,"Under Budget - Review","Over Budget - Review"),"Within Range") -> Within Range
A16: Garage South | B16: Mar-2026 | C16: 118000 | D16: 119810 | E16: =D16-C16 -> 1810 | F16: =IFERROR(E16/C16,0) -> 0.015338983 | G16: =IF(ABS(F16)>Assumptions!$B$6,IF(E16<0,"Under Budget - Review","Over Budget - Review"),"Within Range") -> Within Range
... A40: Valet Service | B40: Sep-2026 | C40: 32200 | D40: 28980 | E40: =D40-C40 -> -3220 | F40: =IFERROR(E40/C40,0) -> -0.1 | G40: =IF(ABS(F40)>Assumptions!$B$6,IF(E40<0,"Under Budget - Review","Over Budget - Review"),"Within Range") -> Under Budget - Review

Sheet Employee_Access
A1: Employee Parking Access vs. Payroll Deductions
A2: Synthetic data | Active permits and deductions are inputs (blue); gap and estimated leakage are formulas
A4: Month | B4: Active Badge Permits | C4: Payroll Deductions Processed | D4: Unbilled Permits | E4: Est. Unbilled Revenue ($) | F4: Status
A5: Jan-2026 | B5: 3235 | C5: 3235 | D5: =B5-C5 -> 0 | E5: =D5*Assumptions!$B$7 -> 0 | F5: =IF(D5=0,"Reconciled",IF(D5>0,"Permits Not Billed - Investigate","Deductions Exceed Permits - Investigate")) -> Reconciled
A6: Feb-2026 | B6: 3234 | C6: 3234 | D6: =B6-C6 -> 0 | E6: =D6*Assumptions!$B$7 -> 0 | F6: =IF(D6=0,"Reconciled",IF(D6>0,"Permits Not Billed - Investigate","Deductions Exceed Permits - Investigate")) -> Reconciled
A7: Mar-2026 | B7: 3221 | C7: 3221 | D7: =B7-C7 -> 0 | E7: =D7*Assumptions!$B$7 -> 0 | F7: =IF(D7=0,"Reconciled",IF(D7>0,"Permits Not Billed - Investigate","Deductions Exceed Permits - Investigate")) -> Reconciled
A8: Apr-2026 | B8: 3241 | C8: 3241 | D8: =B8-C8 -> 0 | E8: =D8*Assumptions!$B$7 -> 0 | F8: =IF(D8=0,"Reconciled",IF(D8>0,"Permits Not Billed - Investigate","Deductions Exceed Permits - Investigate")) -> Reconciled
A9: May-2026 | B9: 3268 | C9: 3260 | D9: =B9-C9 -> 8 | E9: =D9*Assumptions!$B$7 -> 760 | F9: =IF(D9=0,"Reconciled",IF(D9>0,"Permits Not Billed - Investigate","Deductions Exceed Permits - Investigate")) -> Permits Not Billed - Investigate
A10: Jun-2026 | B10: 3249 | C10: 3249 | D10: =B10-C10 -> 0 | E10: =D10*Assumptions!$B$7 -> 0 | F10: =IF(D10=0,"Reconciled",IF(D10>0,"Permits Not Billed - Investigate","Deductions Exceed Permits - Investigate")) -> Reconciled
A11: Jul-2026 | B11: 3231 | C11: 3231 | D11: =B11-C11 -> 0 | E11: =D11*Assumptions!$B$7 -> 0 | F11: =IF(D11=0,"Reconciled",IF(D11>0,"Permits Not Billed - Investigate","Deductions Exceed Permits - Investigate")) -> Reconciled
A12: Aug-2026 | B12: 3249 | C12: 3249 | D12: =B12-C12 -> 0 | E12: =D12*Assumptions!$B$7 -> 0 | F12: =IF(D12=0,"Reconciled",IF(D12>0,"Permits Not Billed - Investigate","Deductions Exceed Permits - Investigate")) -> Reconciled
A13: Sep-2026 | B13: 3255 | C13: 3250 | D13: =B13-C13 -> 5 | E13: =D13*Assumptions!$B$7 -> 475 | F13: =IF(D13=0,"Reconciled",IF(D13>0,"Permits Not Billed - Investigate","Deductions Exceed Permits - Investigate")) -> Permits Not Billed - Investigate
A14: Total | D14: =SUM(D5:D13) -> 13 | E14: =SUM(E5:E13) -> 1235
